baboons/__init__.py
baboons/exception/__init__.py
baboons/module/__init__.py
baboons-0.1.0.dist-info/LICENSE.txt
baboons-0.1.0.dist-info/METADATA
baboons-0.1.0.dist-info/WHEEL
baboons-0.1.0.dist-info/top_level.txt
baboons-0.1.0.dist-info/RECORD
